listdump/__init__.py
listdump/__main__.py
listdump/list_files.py
listdump-0.1.9.dist-info/licenses/LICENCE
listdump-0.1.9.dist-info/METADATA
listdump-0.1.9.dist-info/WHEEL
listdump-0.1.9.dist-info/entry_points.txt
listdump-0.1.9.dist-info/top_level.txt
listdump-0.1.9.dist-info/RECORD
