Metadata-Version: 2.4
Name: listdump
Version: 0.1.9
Summary: List relevant files with content in markdown format
Author-email: Tim Abdiukov <TAbdiukov@gmail.com>
License-Expression: Apache-2.0
Project-URL: Homepage, https://github.com/TAbdiukov/listdump
Project-URL: Source, https://github.com/TAbdiukov/listdump
Project-URL: Issues, https://github.com/TAbdiukov/listdump/issues
Project-URL: Documentation, https://github.com/TAbdiukov/listdump/blob/main/README.md
Requires-Python: >=3.7
License-File: LICENCE
Requires-Dist: pathspec
Dynamic: license-file
